quark_threaded_runtime.py
datawire_quark_threaded-0.3.10.dist-info/DESCRIPTION.rst
datawire_quark_threaded-0.3.10.dist-info/METADATA
datawire_quark_threaded-0.3.10.dist-info/RECORD
datawire_quark_threaded-0.3.10.dist-info/WHEEL
datawire_quark_threaded-0.3.10.dist-info/metadata.json
datawire_quark_threaded-0.3.10.dist-info/top_level.txt
