Metadata-Version: 2.0
Name: datawire-quark-threaded
Version: 0.3.10
Summary: Threaded integration for Python code generated by Quark
Home-page: http://datawire.github.io/quark
Author: datawire.io
Author-email: hello@datawire.io
License: Apache License, Version 2.0
Platform: UNKNOWN
Requires-Dist: ws4py (==0.3.4)
